setup.cfg
setup.py
youtunes
main/__init__.py
main/main.py
youtunes.egg-info/PKG-INFO
youtunes.egg-info/SOURCES.txt
youtunes.egg-info/dependency_links.txt
youtunes.egg-info/requires.txt
youtunes.egg-info/top_level.txt