Metadata-Version: 1.1
Name: youtunes
Version: 0.6
Summary: Multithreaded direct download from youtube to mp3
Home-page: https://github.com/achang97/YouTunes
Author: Andrew Chang
Author-email: achang97@stanford.edu
License: MIT
Download-URL: https://github.com/achang97/youtunes/tarball/0.6
Keywords: download,YouTube,iTunes
Platform: UNKNOWN
Classifier: Operating System :: MacOS
Classifier: License :: OSI Approved :: MIT License
Classifier: Programming Language :: Python :: 2.7
